yalesnotes/__init__.py
yalesnotes/main.py
yalesnotes/res/bareme-2017-2018.csv
yalesnotes/src/__init__.py
yalesnotes/src/core/__init__.py
yalesnotes/src/core/bareme_tools.py
yalesnotes/src/core/parser.py
yalesnotes/src/utils/__init__.py
yalesnotes/src/utils/iterators.py
yalesnotes-0.0.3.dist-info/LICENSE.txt
yalesnotes-0.0.3.dist-info/METADATA
yalesnotes-0.0.3.dist-info/WHEEL
yalesnotes-0.0.3.dist-info/entry_points.txt
yalesnotes-0.0.3.dist-info/top_level.txt
yalesnotes-0.0.3.dist-info/RECORD
